{"sidebar-1":{"search-2":{"title":""},"categories-2":{"title":"","count":0,"hierarchical":0,"dropdown":0},"text-5":{"title":"Text Widget","text":"Suspendisse urna nibh, viverra non, semper suscipit, posuere a, pede.\r\n\r\nDonec nec justo eget felis facilisis fermentum. Aliquam porttitor mauris sit amet orci.\r\n","filter":true},"text-6":{"title":"Flickr Widget","text":"<ul class=\"flickr\">\r\n  <li><a href=\"#\"><img src=\"http:\/\/qkthemes-demo.com\/wordpress\/koncept\/constrction\/vertical\/wp-content\/uploads\/2015\/06\/17.jpg\" alt=\"flickr\"><\/a><\/li>\r\n  <li><a href=\"#\"><img src=\"http:\/\/qkthemes-demo.com\/wordpress\/koncept\/constrction\/vertical\/wp-content\/uploads\/2015\/06\/25.jpg\" alt=\"flickr\"><\/a><\/li>\r\n  <li><a href=\"#\"><img src=\"http:\/\/qkthemes-demo.com\/wordpress\/koncept\/constrction\/vertical\/wp-content\/uploads\/2015\/06\/35.jpg\" alt=\"flickr\"><\/a><\/li>\r\n  <li><a href=\"#\"><img src=\"http:\/\/qkthemes-demo.com\/wordpress\/koncept\/constrction\/vertical\/wp-content\/uploads\/2015\/06\/45.jpg\" alt=\"flickr\"><\/a><\/li>\r\n  <li><a href=\"#\"><img src=\"http:\/\/qkthemes-demo.com\/wordpress\/koncept\/constrction\/vertical\/wp-content\/uploads\/2015\/06\/56.jpg\" alt=\"flickr\"><\/a><\/li>\r\n  <li><a href=\"#\"><img src=\"http:\/\/qkthemes-demo.com\/wordpress\/koncept\/constrction\/vertical\/wp-content\/uploads\/2015\/06\/63.jpg\" alt=\"flickr\"><\/a><\/li><li><a href=\"#\"><img src=\"http:\/\/demo.qkthemes.net\/construct\/wp-content\/uploads\/2015\/11\/16.jpg\" alt=\"\"\/><\/a><\/li>\r\n\t<li><a href=\"#\"><img src=\"http:\/\/demo.qkthemes.net\/construct\/wp-content\/uploads\/2015\/11\/25.jpg\" alt=\"\"\/><\/a><\/li>\r\n<\/ul>","filter":false},"tag_cloud-3":{"title":"Tags","taxonomy":"post_tag"}},"sidebar-service":{"nav_menu-2":{"nav_menu":13}},"footer-1":{"text-2":{"title":"About Us","text":"<p>Duis aute irure dolor in reprehenderit in voluptate velit esse cillum dolore eu fugiat nulla pariatur.<\/p>\r\n<p>Reprehenderit in voluptate velit esse cillum nulla pariatur.<\/p>","filter":false}},"footer-2":{"tag_cloud-2":{"title":"Tags","taxonomy":"post_tag"}},"footer-3":{"text-3":{"title":"Flickr Widget","text":"<ul class=\"flickr-list\">\r\n\t<li><a href=\"#\"><img src=\"http:\/\/demo.qkthemes.net\/construct\/wp-content\/uploads\/2015\/11\/16.jpg\" alt=\"\"\/><\/a><\/li>\r\n\t<li><a href=\"#\"><img src=\"http:\/\/demo.qkthemes.net\/construct\/wp-content\/uploads\/2015\/11\/25.jpg\" alt=\"\"\/><\/a><\/li>\r\n\t<li><a href=\"#\"><img src=\"http:\/\/demo.qkthemes.net\/construct\/wp-content\/uploads\/2015\/11\/34.jpg\" alt=\"\"\/><\/a><\/li>\r\n\t<li><a href=\"#\"><img src=\"http:\/\/demo.qkthemes.net\/construct\/wp-content\/uploads\/2015\/11\/44.jpg\" alt=\"\"\/><\/a><\/li>\r\n\t<li><a href=\"#\"><img src=\"http:\/\/demo.qkthemes.net\/construct\/wp-content\/uploads\/2015\/11\/53.jpg\" alt=\"\"\/><\/a><\/li>\r\n\t<li><a href=\"#\"><img src=\"http:\/\/demo.qkthemes.net\/construct\/wp-content\/uploads\/2015\/11\/61.jpg\" alt=\"\"\/><\/a><\/li>\r\n\t<li><a href=\"#\"><img src=\"http:\/\/demo.qkthemes.net\/construct\/wp-content\/uploads\/2015\/11\/16.jpg\" alt=\"\"\/><\/a><\/li>\r\n\t<li><a href=\"#\"><img src=\"http:\/\/demo.qkthemes.net\/construct\/wp-content\/uploads\/2015\/11\/53.jpg\" alt=\"\"\/><\/a><\/li>\r\n<\/ul>","filter":false}},"footer-4":{"text-4":{"title":"Working Hours","text":"<p class=\"first-par\">You can contact or visit us during working time.<\/p>\r\n<p><span>Tel: <\/span> 1234 - 5678 - 9012<\/p>\r\n<p><span>Email: <\/span> nunforest@gmail.com<\/p>\r\n<p><span>Working Hours: <\/span> 8:00 a.m - 17:00 a.m<\/p>","filter":false}}}